Workbook

Sheet Dashboard
A1: FINANCIËLE COCKPIT | F1: Laatste update: | G1: =NOW()
A3: CRYPTO HOLDINGS | F3: TOP ALERTS
A4: Bitcoin (BTC) | B4: =SUM(tblBTC[BTC Aantal]) | C4: =SUM(tblBTC[BTC Aantal])*XLOOKUP("BTC",tblKoersen[Symbol],tblKoersen[EUR prijs],0) | F4: =IF(Alerts!B4="","",Alerts!B4) | G4: =IF(Alerts!B4="","",Alerts!H4)
A5: Dogecoin (DOGE) | B5: =SUM(tblDOGE[DOGE Aantal]) | C5: =SUM(tblDOGE[DOGE Aantal])*XLOOKUP("DOGE",tblKoersen[Symbol],tblKoersen[EUR prijs],0) | F5: =IF(Alerts!B5="","",Alerts!B5) | G5: =IF(Alerts!B5="","",Alerts!H5)
A6: Totaal Crypto | C6: =C4+C5 | F6: =IF(Alerts!B6="","",Alerts!B6) | G6: =IF(Alerts!B6="","",Alerts!H6)
A7: waarvan Spot: | C7: =SUMIF(tblBTC[Type],"Spot",tblBTC[BTC Aantal])*XLOOKUP("BTC",tblKoersen[Symbol],tblKoersen[EUR prijs],0)+SUMIF(tblDOGE[Type],"Spot",tblDOGE[DOGE Aantal])*XLOOKUP("DOGE",tblKoersen[Symbol],tblKoersen[EUR prijs],0) | F7: → Zie Alerts sheet voor details
A8: waarvan Collateral: | C8: =SUMIF(tblBTC[Type],"Collateral",tblBTC[BTC Aantal])*XLOOKUP("BTC",tblKoersen[Symbol],tblKoersen[EUR prijs],0)+SUMIF(tblDOGE[Type],"Collateral",tblDOGE[DOGE Aantal])*XLOOKUP("DOGE",tblKoersen[Symbol],tblKoersen[EUR prijs],0)
A11: VASTGOED | F11: STRESS TEST
A12: Totale Waarde | C12: =SUM(tblVastgoed[Waarde(EUR)]) | F12: Scenario 1: | G12: =XLOOKUP("StressBTCDown1",tblSettings[Parameter],tblSettings[Waarde]) | H12: ='BTC als Onderpand'!F18
A13: Hypotheken | C13: =SUM(tblVastgoed[Hypotheek(EUR)]) | F13: Scenario 2: | G13: =XLOOKUP("StressBTCDown2",tblSettings[Parameter],tblSettings[Waarde]) | H13: ='BTC als Onderpand'!F19
A14: Overige Leningen | C14: =SUM(tblVastgoed[Overige Leningen(EUR)])
A15: Netto Vastgoed | C15: =SUM(tblVastgoed[Netto Waarde])
F16: KOERSEN
F17: BTC | G17: =XLOOKUP("BTC",tblKoersen[Symbol],tblKoersen[EUR prijs],0)
A18: CASH & LENINGEN | F18: DOGE | G18: =XLOOKUP("DOGE",tblKoersen[Symbol],tblKoersen[EUR prijs],0)
A19: Cash & Overig | C19: =SUM(tblCash[Bedrag(EUR)])
A20: BTC-leningen | C20: =SUMIF(tblLeningen[OnderpandType],"BTC",tblLeningen[Openstaand(EUR)])
A21: Overige Leningen | C21: =SUMIF(tblLeningen[OnderpandType],"Vastgoed",tblLeningen[Openstaand(EUR)]) | F21: BTC LENING STATUS
A22: Cash Buffer | C22: ='Cash & Overig'!H5 | F22: Eerste lening:
F23: LoanID | G23: ='BTC als Onderpand'!A4
F24: Current LTV | G24: ='BTC als Onderpand'!G4
A25: NETTO VERMOGEN | F25: Distance to Liq | G25: ='BTC als Onderpand'!I4
A26: Totaal Activa | C26: =C6+C12+C19 | F26: Status | G26: ='BTC als Onderpand'!J4
A27: Totaal Schulden | C27: =C13+C14+C20+C21
A28: NETTO VERMOGEN | C28: =C26-C27
F29: CASHFLOW
F30: Inkomsten/maand | G30: =SUM(tblInkomsten[Netto/maand])
F31: Uitgaven/maand | G31: =SUM(tblMaandlasten[Bedrag(EUR)])
F32: Netto Cashflow | G32: =G30-G31
F33: Spaarquote | G33: =IF(G30=0,0,G32/G30)
F35: Box 3 belasting | G35: =Belastingen!B19

Sheet Alerts
A1: Alerts - Inzichten & Acties
A3: Date | B3: Severity | C3: Category | D3: Item | E3: Metric | F3: Value | G3: Threshold | H3: Insight | I3: SuggestedAction
A4: =TODAY() | B4: =IF('BTC als Onderpand'!J4="RISK","CRITICAL",IF('BTC als Onderpand'!J4="ALERT","ALERT","")) | C4: =IF(B4="","","BTC Lening") | D4: =IF(B4="","",'BTC als Onderpand'!A4) | E4: =IF(B4="","","LTV") | F4: =IF(B4="","",'BTC als Onderpand'!G4) | G4: =IF(B4="","",'BTC als Onderpand'!H4) | H4: =IF(B4="","",IF(B4="CRITICAL","LTV kritiek - liquidatie dreigt!","LTV te hoog - actie vereist")) | I4: =IF(B4="","",CONCAT("Los ",TEXT('BTC als Onderpand'!K4,"€ #.##0")," af OF stort ",TEXT('BTC als Onderpand'!L4,"0.0000")," BTC bij"))
A5: =TODAY() | B5: =IF('Cash & Overig'!H5<XLOOKUP("CashBufferMonthsTarget",tblSettings[Parameter],tblSettings[Waarde]),"ALERT","") | C5: =IF(B5="","","Cash Buffer") | D5: =IF(B5="","","Totaal Cash") | E5: =IF(B5="","","Maanden buffer") | F5: =IF(B5="","",'Cash & Overig'!H5) | G5: =IF(B5="","",XLOOKUP("CashBufferMonthsTarget",tblSettings[Parameter],tblSettings[Waarde])) | H5: =IF(B5="","","Cashbuffer onder target - verhoog reserves") | I5: =IF(B5="","",CONCAT("Verhoog cash met €",TEXT((B7-'Cash & Overig'!H5)*'Cash & Overig'!H4,"#.##0")))
A6: =TODAY() | B6: =LET(btc_val,SUM(tblBTC[BTC Aantal])*XLOOKUP("BTC",tblKoersen[Symbol],tblKoersen[EUR prijs],0),doge_val,SUM(tblDOGE[DOGE Aantal])*XLOOKUP("DOGE",tblKoersen[Symbol],tblKoersen[EUR prijs],0),crypto_total,btc_val+doge_val,vastgoed_val,SUM(tblVastgoed[Waarde(EUR)]),total,crypto_total+vastgoed_val+SUM(tblCash[Bedrag(EUR)]),concentration,IF(total=0,0,crypto_total/total),threshold,XLOOKUP("ConcentrationAlertPct",tblSettings[Parameter],tblSettings[Waarde]),IF(concentration>threshold,"ALERT","")) | C6: =IF(B6="","","Concentratie") | D6: =IF(B6="","","Crypto Allocatie") | E6: =IF(B6="","","% van totaal") | F6: =IF(B6="","",LET(btc_val,SUM(tblBTC[BTC Aantal])*XLOOKUP("BTC",tblKoersen[Symbol],tblKoersen[EUR prijs],0),doge_val,SUM(tblDOGE[DOGE Aantal])*XLOOKUP("DOGE",tblKoersen[Symbol],tblKoersen[EUR prijs],0),crypto_total,btc_val+doge_val,vastgoed_val,SUM(tblVastgoed[Waarde(EUR)]),total,crypto_total+vastgoed_val+SUM(tblCash[Bedrag(EUR)]),IF(total=0,0,crypto_total/total))) | G6: =IF(B6="","",XLOOKUP("ConcentrationAlertPct",tblSettings[Parameter],tblSettings[Waarde])) | H6: =IF(B6="","","Crypto-allocatie te hoog - overweeg diversificatie") | I6: =IF(B6="","","Overweeg winst te nemen of te diversifieren naar andere assets")
A7: =TODAY() | B7: =IF(OR('BTC als Onderpand'!F18="RISK",'BTC als Onderpand'!F18="LIQUIDATION"),"ALERT","") | C7: =IF(B7="","","Stress Test") | D7: =IF(B7="","","Scenario 1") | E7: =IF(B7="","","LTV bij daling") | F7: =IF(B7="","",'BTC als Onderpand'!E18) | G7: =IF(B7="","",'BTC als Onderpand'!H4) | H7: =IF(B7="","",CONCAT("Bij ",TEXT('BTC als Onderpand'!B18,"0%")," BTC-daling: ",'BTC als Onderpand'!F18)) | I7: =IF(B7="","","Overweeg preventief af te lossen of collateral te verhogen")
A8: =TODAY() | B8: =IF(OR('BTC als Onderpand'!F19="RISK",'BTC als Onderpand'!F19="LIQUIDATION"),"ALERT","") | C8: =IF(B8="","","Stress Test") | D8: =IF(B8="","","Scenario 2") | E8: =IF(B8="","","LTV bij daling") | F8: =IF(B8="","",'BTC als Onderpand'!E19) | G8: =IF(B8="","",'BTC als Onderpand'!H4) | H8: =IF(B8="","",CONCAT("Bij ",TEXT('BTC als Onderpand'!B19,"0%")," BTC-daling: ",'BTC als Onderpand'!F19)) | I8: =IF(B8="","","Actie vereist: liquidatierisico bij sterke daling")
A17: LEGENDA:
A18: • Alleen actieve alerts worden getoond (lege rijen = geen alert)
A19: • CRITICAL = Directe actie vereist
A20: • ALERT = Aandacht vereist
A21: • INFO = Ter informatie

Sheet Instellingen
A1: Instellingen - Configuratie Parameters
A3: Parameter | B3: Waarde | C3: Eenheid | D3: Toelichting | G3: Lening-Onderpand Koppeling
A4: RefreshMinutes | B4: 10 | C4: minuten | D4: Interval voor automatische koers-refresh in Excel | G4: LoanID | H4: CollateralType | I4: CollateralRef | J4: Notes
A5: TargetLTV_BTC | B5: 0.3 | C5: ratio | D5: Doel-LTV voor BTC-leningen (30%) | G5: L001 | H5: BTC | I5: BlockFi | J5: 0.25 BTC als onderpand
A6: AlertBuffer_BTC | B6: 0.1 | C6: ratio | D6: Afstand tot liquidatie waarbij ALERT getriggerd wordt
A7: RiskBuffer_BTC | B7: 0.05 | C7: ratio | D7: Afstand tot liquidatie waarbij RISK getriggerd wordt
A8: DefaultLiquidationLTV_BTC | B8: 0.5 | C8: ratio | D8: Standaard liquidatie-LTV voor BTC-leningen (50%)
A9: CashBufferMonthsTarget | B9: 6 | C9: maanden | D9: Minimaal aantal maanden cashbuffer
A10: MaxDebtServiceRatio | B10: 0.35 | C10: ratio | D10: Maximale schuld-service ratio (35%)
A11: MonthlyExpenses | B11: 5000 | C11: EUR | D11: Geschatte maandelijkse uitgaven (voor cashbuffer berekening)
A12: StressBTCDown1 | B12: -0.2 | C12: percentage | D12: Stress scenario 1: BTC daalt met 20%
A13: StressBTCDown2 | B13: -0.4 | C13: percentage | D13: Stress scenario 2: BTC daalt met 40%
A14: ConcentrationAlertPct | B14: 0.6 | C14: ratio | D14: Alert als crypto > 60% van totaal vermogen

Sheet Koersen
A1: Koersen - Live Prijzen
A3: Asset | B3: Symbol | C3: EUR prijs | D3: USD prijs | E3: Laatste update
A4: Bitcoin | B4: BTC | C4: 58000 | D4: 62500 | E4: =NOW()
A5: Dogecoin | B5: DOGE | C5: 0.12 | D5: 0.13 | E5: =NOW()
A10: Let op: Koersen worden bijgewerkt via Power Query. Zie 'Koers-Setup' voor instructies.

Sheet Koers-Setup
A1: Koers-Setup - Power Query Instructies
A3: INSTRUCTIES VOOR AUTOMATISCHE KOERSEN VIA POWER QUERY
A5: 1. POWER QUERY INSTELLEN
A6: a) Ga naar Data > Get Data > From Web
A7: b) Voer de volgende URL in:
A8: https://api.coingecko.com/api/v3/simple/price?ids=bitcoin,dogecoin&vs_currencies=eur,usd
A9: c) Klik OK en wacht tot de data is geladen
A11: 2. DATA TRANSFORMEREN
A12: a) In Power Query Editor: Transform > To Table
A13: b) Expand de kolommen om bitcoin.eur, bitcoin.usd, dogecoin.eur, dogecoin.usd te krijgen
A14: c) Hernoem kolommen naar: Asset, EUR prijs, USD prijs
A15: d) Voeg een kolom toe voor Laatste update: = DateTime.LocalNow()
... A35: De berekeningen en alerts werken dan nog steeds correct.

Sheet Bitcoin Holdings
A1: Bitcoin Holdings
G2: Totaal BTC: | H2: =SUM(tblBTC[BTC Aantal])
A3: Datum | B3: Wallet/Platform | C3: BTC Aantal | D3: Type | E3: Opmerking | G3: Spot: | H3: =SUMIF(tblBTC[Type],"Spot",tblBTC[BTC Aantal])
A4: 2024-01-15 | B4: Hardware Wallet | C4: 0.5 | D4: Spot | E4: Cold storage | G4: Collateral: | H4: =SUMIF(tblBTC[Type],"Collateral",tblBTC[BTC Aantal])
A5: 2024-02-01 | B5: BlockFi | C5: 0.25 | D5: Collateral | E5: Onderpand voor lening L001
A6: 2024-03-10 | B6: Bitvavo | C6: 0.15 | D6: Spot | E6: Exchange

Sheet Dogecoin Holdings
A1: Dogecoin Holdings
G2: Totaal DOGE: | H2: =SUM(tblDOGE[DOGE Aantal])
A3: Datum | B3: Wallet/Platform | C3: DOGE Aantal | D3: Type | E3: Opmerking
A4: 2024-01-20 | B4: Bitvavo | C4: 10000 | D4: Spot
A5: 2024-02-15 | B5: Kraken | C5: 5000 | D5: Spot

Sheet Vastgoed
A1: Vastgoed - Onroerend Goed
I2: Totale Waarde: | J2: =SUM(tblVastgoed[Waarde(EUR)])
A3: Pand | B3: Adres | C3: Type | D3: Waarde(EUR) | E3: Hypotheek(EUR) | F3: Overige Leningen(EUR) | G3: Netto Waarde | I3: Totale Schuld: | J3: =SUM(tblVastgoed[Hypotheek(EUR)])+SUM(tblVastgoed[Overige Leningen(EUR)])
A4: Woning Amsterdam | B4: Voorbeeldstraat 123, Amsterdam | C4: Eigen woning | D4: 650000 | E4: 400000 | F4: 0 | G4: =IF(D4="","",D4-E4-F4) | I4: Netto Waarde: | J4: =SUM(tblVastgoed[Netto Waarde])
A5: Appartement Utrecht | B5: Voorbeeldlaan 45, Utrecht | C5: Verhuur | D5: 350000 | E5: 200000 | F5: 25000 | G5: =IF(D5="","",D5-E5-F5)
G6: =IF(D6="","",D6-E6-F6)
G7: =IF(D7="","",D7-E7-F7)
G8: =IF(D8="","",D8-E8-F8)
G9: =IF(D9="","",D9-E9-F9)
G10: =IF(D10="","",D10-E10-F10)
G11: =IF(D11="","",D11-E11-F11)
G12: =IF(D12="","",D12-E12-F12)
G13: =IF(D13="","",D13-E13-F13)
G14: =IF(D14="","",D14-E14-F14)
G15: =IF(D15="","",D15-E15-F15)
G16: =IF(D16="","",D16-E16-F16)
G17: =IF(D17="","",D17-E17-F17)
... G19: =IF(D19="","",D19-E19-F19)

Sheet Leningen
A1: Leningen - Overzicht
M2: Totaal Openstaand: | N2: =SUM(tblLeningen[Openstaand(EUR)])
A3: LoanID | B3: Datum | C3: OnderpandType | D3: OnderpandRef | E3: Lener | F3: Hoofdsom(EUR) | G3: Openstaand(EUR) | H3: Rente% | I3: Looptijd | J3: LiquidatieLTV | K3: Opmerking | M3: BTC-leningen: | N3: =SUMIF(tblLeningen[OnderpandType],"BTC",tblLeningen[Openstaand(EUR)])
A4: L001 | B4: 2024-02-01 | C4: BTC | D4: BlockFi | E4: BlockFi | F4: 5000 | G4: 4800 | H4: 0.08 | I4: 12 maanden | J4: 0.5 | K4: BTC-backed loan | M4: Vastgoed-leningen: | N4: =SUMIF(tblLeningen[OnderpandType],"Vastgoed",tblLeningen[Openstaand(EUR)])
A5: L002 | B5: 2023-06-01 | C5: Vastgoed | D5: Appartement Utrecht | E5: ING Bank | F5: 30000 | G5: 25000 | H5: 0.045 | I5: 60 maanden | K5: Verbouwingslening

Sheet BTC als Onderpand
A1: BTC als Onderpand - LTV Monitor
A3: LoanID | B3: Platform/Lener | C3: BTC Onderpand | D3: Openstaand(EUR) | E3: BTC prijs(EUR) | F3: CollateralValue(EUR) | G3: CurrentLTV | H3: LiquidationLTV | I3: DistanceToLiq | J3: Status | K3: RequiredRepayEUR | L3: RequiredAddBTC
A4: =IFERROR(INDEX(tblLeningen[LoanID],SMALL(IF(tblLeningen[OnderpandType]="BTC",ROW(tblLeningen[OnderpandType])-ROW(tblLeningen[[#Headers],[OnderpandType]])),1)),"") | B4: =IF(A4="","",XLOOKUP(A4,tblLeningen[LoanID],tblLeningen[Lener],"")) | C4: =IF(A4="","",IFERROR(SUMIF(tblBTC[Wallet/Platform],XLOOKUP(A4,tblLeningen[LoanID],tblLeningen[OnderpandRef],""),tblBTC[BTC Aantal]),0)) | D4: =IF(A4="","",XLOOKUP(A4,tblLeningen[LoanID],tblLeningen[Openstaand(EUR)],0)) | E4: =IF(A4="","",XLOOKUP("BTC",tblKoersen[Symbol],tblKoersen[EUR prijs],0)) | F4: =IF(A4="","",C4*E4) | G4: =IF(OR(A4="",F4=0),"",D4/F4) | H4: =IF(A4="","",IF(XLOOKUP(A4,tblLeningen[LoanID],tblLeningen[LiquidatieLTV],"")="",XLOOKUP("DefaultLiquidationLTV_BTC",tblSettings[Parameter],tblSettings[Waarde]),XLOOKUP(A4,tblLeningen[LoanID],tblLeningen[LiquidatieLTV]))) | I4: =IF(OR(A4="",G4=""),"",H4-G4) | J4: =IF(A4="","",IF(I4<=XLOOKUP("RiskBuffer_BTC",tblSettings[Parameter],tblSettings[Waarde]),"RISK",IF(I4<=XLOOKUP("AlertBuffer_BTC",tblSettings[Parameter],tblSettings[Waarde]),"ALERT","OK"))) | K4: =IF(OR(A4="",J4="OK"),"",MAX(0,D4-(XLOOKUP("TargetLTV_BTC",tblSettings[Parameter],tblSettings[Waarde])*F4))) | L4: =IF(OR(A4="",J4="OK"),"",MAX(0,(D4/XLOOKUP("TargetLTV_BTC",tblSettings[Parameter],tblSettings[Waarde])-F4)/E4))
A5: =IFERROR(INDEX(tblLeningen[LoanID],SMALL(IF(tblLeningen[OnderpandType]="BTC",ROW(tblLeningen[OnderpandType])-ROW(tblLeningen[[#Headers],[OnderpandType]])),2)),"") | B5: =IF(A5="","",XLOOKUP(A5,tblLeningen[LoanID],tblLeningen[Lener],"")) | C5: =IF(A5="","",IFERROR(SUMIF(tblBTC[Wallet/Platform],XLOOKUP(A5,tblLeningen[LoanID],tblLeningen[OnderpandRef],""),tblBTC[BTC Aantal]),0)) | D5: =IF(A5="","",XLOOKUP(A5,tblLeningen[LoanID],tblLeningen[Openstaand(EUR)],0)) | E5: =IF(A5="","",XLOOKUP("BTC",tblKoersen[Symbol],tblKoersen[EUR prijs],0)) | F5: =IF(A5="","",C5*E5) | G5: =IF(OR(A5="",F5=0),"",D5/F5) | H5: =IF(A5="","",IF(XLOOKUP(A5,tblLeningen[LoanID],tblLeningen[LiquidatieLTV],"")="",XLOOKUP("DefaultLiquidationLTV_BTC",tblSettings[Parameter],tblSettings[Waarde]),XLOOKUP(A5,tblLeningen[LoanID],tblLeningen[LiquidatieLTV]))) | I5: =IF(OR(A5="",G5=""),"",H5-G5) | J5: =IF(A5="","",IF(I5<=XLOOKUP("RiskBuffer_BTC",tblSettings[Parameter],tblSettings[Waarde]),"RISK",IF(I5<=XLOOKUP("AlertBuffer_BTC",tblSettings[Parameter],tblSettings[Waarde]),"ALERT","OK"))) | K5: =IF(OR(A5="",J5="OK"),"",MAX(0,D5-(XLOOKUP("TargetLTV_BTC",tblSettings[Parameter],tblSettings[Waarde])*F5))) | L5: =IF(OR(A5="",J5="OK"),"",MAX(0,(D5/XLOOKUP("TargetLTV_BTC",tblSettings[Parameter],tblSettings[Waarde])-F5)/E5))
A6: =IFERROR(INDEX(tblLeningen[LoanID],SMALL(IF(tblLeningen[OnderpandType]="BTC",ROW(tblLeningen[OnderpandType])-ROW(tblLeningen[[#Headers],[OnderpandType]])),3)),"") | B6: =IF(A6="","",XLOOKUP(A6,tblLeningen[LoanID],tblLeningen[Lener],"")) | C6: =IF(A6="","",IFERROR(SUMIF(tblBTC[Wallet/Platform],XLOOKUP(A6,tblLeningen[LoanID],tblLeningen[OnderpandRef],""),tblBTC[BTC Aantal]),0)) | D6: =IF(A6="","",XLOOKUP(A6,tblLeningen[LoanID],tblLeningen[Openstaand(EUR)],0)) | E6: =IF(A6="","",XLOOKUP("BTC",tblKoersen[Symbol],tblKoersen[EUR prijs],0)) | F6: =IF(A6="","",C6*E6) | G6: =IF(OR(A6="",F6=0),"",D6/F6) | H6: =IF(A6="","",IF(XLOOKUP(A6,tblLeningen[LoanID],tblLeningen[LiquidatieLTV],"")="",XLOOKUP("DefaultLiquidationLTV_BTC",tblSettings[Parameter],tblSettings[Waarde]),XLOOKUP(A6,tblLeningen[LoanID],tblLeningen[LiquidatieLTV]))) | I6: =IF(OR(A6="",G6=""),"",H6-G6) | J6: =IF(A6="","",IF(I6<=XLOOKUP("RiskBuffer_BTC",tblSettings[Parameter],tblSettings[Waarde]),"RISK",IF(I6<=XLOOKUP("AlertBuffer_BTC",tblSettings[Parameter],tblSettings[Waarde]),"ALERT","OK"))) | K6: =IF(OR(A6="",J6="OK"),"",MAX(0,D6-(XLOOKUP("TargetLTV_BTC",tblSettings[Parameter],tblSettings[Waarde])*F6))) | L6: =IF(OR(A6="",J6="OK"),"",MAX(0,(D6/XLOOKUP("TargetLTV_BTC",tblSettings[Parameter],tblSettings[Waarde])-F6)/E6))
A7: =IFERROR(INDEX(tblLeningen[LoanID],SMALL(IF(tblLeningen[OnderpandType]="BTC",ROW(tblLeningen[OnderpandType])-ROW(tblLeningen[[#Headers],[OnderpandType]])),4)),"") | B7: =IF(A7="","",XLOOKUP(A7,tblLeningen[LoanID],tblLeningen[Lener],"")) | C7: =IF(A7="","",IFERROR(SUMIF(tblBTC[Wallet/Platform],XLOOKUP(A7,tblLeningen[LoanID],tblLeningen[OnderpandRef],""),tblBTC[BTC Aantal]),0)) | D7: =IF(A7="","",XLOOKUP(A7,tblLeningen[LoanID],tblLeningen[Openstaand(EUR)],0)) | E7: =IF(A7="","",XLOOKUP("BTC",tblKoersen[Symbol],tblKoersen[EUR prijs],0)) | F7: =IF(A7="","",C7*E7) | G7: =IF(OR(A7="",F7=0),"",D7/F7) | H7: =IF(A7="","",IF(XLOOKUP(A7,tblLeningen[LoanID],tblLeningen[LiquidatieLTV],"")="",XLOOKUP("DefaultLiquidationLTV_BTC",tblSettings[Parameter],tblSettings[Waarde]),XLOOKUP(A7,tblLeningen[LoanID],tblLeningen[LiquidatieLTV]))) | I7: =IF(OR(A7="",G7=""),"",H7-G7) | J7: =IF(A7="","",IF(I7<=XLOOKUP("RiskBuffer_BTC",tblSettings[Parameter],tblSettings[Waarde]),"RISK",IF(I7<=XLOOKUP("AlertBuffer_BTC",tblSettings[Parameter],tblSettings[Waarde]),"ALERT","OK"))) | K7: =IF(OR(A7="",J7="OK"),"",MAX(0,D7-(XLOOKUP("TargetLTV_BTC",tblSettings[Parameter],tblSettings[Waarde])*F7))) | L7: =IF(OR(A7="",J7="OK"),"",MAX(0,(D7/XLOOKUP("TargetLTV_BTC",tblSettings[Parameter],tblSettings[Waarde])-F7)/E7))
A8: =IFERROR(INDEX(tblLeningen[LoanID],SMALL(IF(tblLeningen[OnderpandType]="BTC",ROW(tblLeningen[OnderpandType])-ROW(tblLeningen[[#Headers],[OnderpandType]])),5)),"") | B8: =IF(A8="","",XLOOKUP(A8,tblLeningen[LoanID],tblLeningen[Lener],"")) | C8: =IF(A8="","",IFERROR(SUMIF(tblBTC[Wallet/Platform],XLOOKUP(A8,tblLeningen[LoanID],tblLeningen[OnderpandRef],""),tblBTC[BTC Aantal]),0)) | D8: =IF(A8="","",XLOOKUP(A8,tblLeningen[LoanID],tblLeningen[Openstaand(EUR)],0)) | E8: =IF(A8="","",XLOOKUP("BTC",tblKoersen[Symbol],tblKoersen[EUR prijs],0)) | F8: =IF(A8="","",C8*E8) | G8: =IF(OR(A8="",F8=0),"",D8/F8) | H8: =IF(A8="","",IF(XLOOKUP(A8,tblLeningen[LoanID],tblLeningen[LiquidatieLTV],"")="",XLOOKUP("DefaultLiquidationLTV_BTC",tblSettings[Parameter],tblSettings[Waarde]),XLOOKUP(A8,tblLeningen[LoanID],tblLeningen[LiquidatieLTV]))) | I8: =IF(OR(A8="",G8=""),"",H8-G8) | J8: =IF(A8="","",IF(I8<=XLOOKUP("RiskBuffer_BTC",tblSettings[Parameter],tblSettings[Waarde]),"RISK",IF(I8<=XLOOKUP("AlertBuffer_BTC",tblSettings[Parameter],tblSettings[Waarde]),"ALERT","OK"))) | K8: =IF(OR(A8="",J8="OK"),"",MAX(0,D8-(XLOOKUP("TargetLTV_BTC",tblSettings[Parameter],tblSettings[Waarde])*F8))) | L8: =IF(OR(A8="",J8="OK"),"",MAX(0,(D8/XLOOKUP("TargetLTV_BTC",tblSettings[Parameter],tblSettings[Waarde])-F8)/E8))
A9: =IFERROR(INDEX(tblLeningen[LoanID],SMALL(IF(tblLeningen[OnderpandType]="BTC",ROW(tblLeningen[OnderpandType])-ROW(tblLeningen[[#Headers],[OnderpandType]])),6)),"") | B9: =IF(A9="","",XLOOKUP(A9,tblLeningen[LoanID],tblLeningen[Lener],"")) | C9: =IF(A9="","",IFERROR(SUMIF(tblBTC[Wallet/Platform],XLOOKUP(A9,tblLeningen[LoanID],tblLeningen[OnderpandRef],""),tblBTC[BTC Aantal]),0)) | D9: =IF(A9="","",XLOOKUP(A9,tblLeningen[LoanID],tblLeningen[Openstaand(EUR)],0)) | E9: =IF(A9="","",XLOOKUP("BTC",tblKoersen[Symbol],tblKoersen[EUR prijs],0)) | F9: =IF(A9="","",C9*E9) | G9: =IF(OR(A9="",F9=0),"",D9/F9) | H9: =IF(A9="","",IF(XLOOKUP(A9,tblLeningen[LoanID],tblLeningen[LiquidatieLTV],"")="",XLOOKUP("DefaultLiquidationLTV_BTC",tblSettings[Parameter],tblSettings[Waarde]),XLOOKUP(A9,tblLeningen[LoanID],tblLeningen[LiquidatieLTV]))) | I9: =IF(OR(A9="",G9=""),"",H9-G9) | J9: =IF(A9="","",IF(I9<=XLOOKUP("RiskBuffer_BTC",tblSettings[Parameter],tblSettings[Waarde]),"RISK",IF(I9<=XLOOKUP("AlertBuffer_BTC",tblSettings[Parameter],tblSettings[Waarde]),"ALERT","OK"))) | K9: =IF(OR(A9="",J9="OK"),"",MAX(0,D9-(XLOOKUP("TargetLTV_BTC",tblSettings[Parameter],tblSettings[Waarde])*F9))) | L9: =IF(OR(A9="",J9="OK"),"",MAX(0,(D9/XLOOKUP("TargetLTV_BTC",tblSettings[Parameter],tblSettings[Waarde])-F9)/E9))
A10: =IFERROR(INDEX(tblLeningen[LoanID],SMALL(IF(tblLeningen[OnderpandType]="BTC",ROW(tblLeningen[OnderpandType])-ROW(tblLeningen[[#Headers],[OnderpandType]])),7)),"") | B10: =IF(A10="","",XLOOKUP(A10,tblLeningen[LoanID],tblLeningen[Lener],"")) | C10: =IF(A10="","",IFERROR(SUMIF(tblBTC[Wallet/Platform],XLOOKUP(A10,tblLeningen[LoanID],tblLeningen[OnderpandRef],""),tblBTC[BTC Aantal]),0)) | D10: =IF(A10="","",XLOOKUP(A10,tblLeningen[LoanID],tblLeningen[Openstaand(EUR)],0)) | E10: =IF(A10="","",XLOOKUP("BTC",tblKoersen[Symbol],tblKoersen[EUR prijs],0)) | F10: =IF(A10="","",C10*E10) | G10: =IF(OR(A10="",F10=0),"",D10/F10) | H10: =IF(A10="","",IF(XLOOKUP(A10,tblLeningen[LoanID],tblLeningen[LiquidatieLTV],"")="",XLOOKUP("DefaultLiquidationLTV_BTC",tblSettings[Parameter],tblSettings[Waarde]),XLOOKUP(A10,tblLeningen[LoanID],tblLeningen[LiquidatieLTV]))) | I10: =IF(OR(A10="",G10=""),"",H10-G10) | J10: =IF(A10="","",IF(I10<=XLOOKUP("RiskBuffer_BTC",tblSettings[Parameter],tblSettings[Waarde]),"RISK",IF(I10<=XLOOKUP("AlertBuffer_BTC",tblSettings[Parameter],tblSettings[Waarde]),"ALERT","OK"))) | K10: =IF(OR(A10="",J10="OK"),"",MAX(0,D10-(XLOOKUP("TargetLTV_BTC",tblSettings[Parameter],tblSettings[Waarde])*F10))) | L10: =IF(OR(A10="",J10="OK"),"",MAX(0,(D10/XLOOKUP("TargetLTV_BTC",tblSettings[Parameter],tblSettings[Waarde])-F10)/E10))
A11: =IFERROR(INDEX(tblLeningen[LoanID],SMALL(IF(tblLeningen[OnderpandType]="BTC",ROW(tblLeningen[OnderpandType])-ROW(tblLeningen[[#Headers],[OnderpandType]])),8)),"") | B11: =IF(A11="","",XLOOKUP(A11,tblLeningen[LoanID],tblLeningen[Lener],"")) | C11: =IF(A11="","",IFERROR(SUMIF(tblBTC[Wallet/Platform],XLOOKUP(A11,tblLeningen[LoanID],tblLeningen[OnderpandRef],""),tblBTC[BTC Aantal]),0)) | D11: =IF(A11="","",XLOOKUP(A11,tblLeningen[LoanID],tblLeningen[Openstaand(EUR)],0)) | E11: =IF(A11="","",XLOOKUP("BTC",tblKoersen[Symbol],tblKoersen[EUR prijs],0)) | F11: =IF(A11="","",C11*E11) | G11: =IF(OR(A11="",F11=0),"",D11/F11) | H11: =IF(A11="","",IF(XLOOKUP(A11,tblLeningen[LoanID],tblLeningen[LiquidatieLTV],"")="",XLOOKUP("DefaultLiquidationLTV_BTC",tblSettings[Parameter],tblSettings[Waarde]),XLOOKUP(A11,tblLeningen[LoanID],tblLeningen[LiquidatieLTV]))) | I11: =IF(OR(A11="",G11=""),"",H11-G11) | J11: =IF(A11="","",IF(I11<=XLOOKUP("RiskBuffer_BTC",tblSettings[Parameter],tblSettings[Waarde]),"RISK",IF(I11<=XLOOKUP("AlertBuffer_BTC",tblSettings[Parameter],tblSettings[Waarde]),"ALERT","OK"))) | K11: =IF(OR(A11="",J11="OK"),"",MAX(0,D11-(XLOOKUP("TargetLTV_BTC",tblSettings[Parameter],tblSettings[Waarde])*F11))) | L11: =IF(OR(A11="",J11="OK"),"",MAX(0,(D11/XLOOKUP("TargetLTV_BTC",tblSettings[Parameter],tblSettings[Waarde])-F11)/E11))
A12: =IFERROR(INDEX(tblLeningen[LoanID],SMALL(IF(tblLeningen[OnderpandType]="BTC",ROW(tblLeningen[OnderpandType])-ROW(tblLeningen[[#Headers],[OnderpandType]])),9)),"") | B12: =IF(A12="","",XLOOKUP(A12,tblLeningen[LoanID],tblLeningen[Lener],"")) | C12: =IF(A12="","",IFERROR(SUMIF(tblBTC[Wallet/Platform],XLOOKUP(A12,tblLeningen[LoanID],tblLeningen[OnderpandRef],""),tblBTC[BTC Aantal]),0)) | D12: =IF(A12="","",XLOOKUP(A12,tblLeningen[LoanID],tblLeningen[Openstaand(EUR)],0)) | E12: =IF(A12="","",XLOOKUP("BTC",tblKoersen[Symbol],tblKoersen[EUR prijs],0)) | F12: =IF(A12="","",C12*E12) | G12: =IF(OR(A12="",F12=0),"",D12/F12) | H12: =IF(A12="","",IF(XLOOKUP(A12,tblLeningen[LoanID],tblLeningen[LiquidatieLTV],"")="",XLOOKUP("DefaultLiquidationLTV_BTC",tblSettings[Parameter],tblSettings[Waarde]),XLOOKUP(A12,tblLeningen[LoanID],tblLeningen[LiquidatieLTV]))) | I12: =IF(OR(A12="",G12=""),"",H12-G12) | J12: =IF(A12="","",IF(I12<=XLOOKUP("RiskBuffer_BTC",tblSettings[Parameter],tblSettings[Waarde]),"RISK",IF(I12<=XLOOKUP("AlertBuffer_BTC",tblSettings[Parameter],tblSettings[Waarde]),"ALERT","OK"))) | K12: =IF(OR(A12="",J12="OK"),"",MAX(0,D12-(XLOOKUP("TargetLTV_BTC",tblSettings[Parameter],tblSettings[Waarde])*F12))) | L12: =IF(OR(A12="",J12="OK"),"",MAX(0,(D12/XLOOKUP("TargetLTV_BTC",tblSettings[Parameter],tblSettings[Waarde])-F12)/E12))
A13: =IFERROR(INDEX(tblLeningen[LoanID],SMALL(IF(tblLeningen[OnderpandType]="BTC",ROW(tblLeningen[OnderpandType])-ROW(tblLeningen[[#Headers],[OnderpandType]])),10)),"") | B13: =IF(A13="","",XLOOKUP(A13,tblLeningen[LoanID],tblLeningen[Lener],"")) | C13: =IF(A13="","",IFERROR(SUMIF(tblBTC[Wallet/Platform],XLOOKUP(A13,tblLeningen[LoanID],tblLeningen[OnderpandRef],""),tblBTC[BTC Aantal]),0)) | D13: =IF(A13="","",XLOOKUP(A13,tblLeningen[LoanID],tblLeningen[Openstaand(EUR)],0)) | E13: =IF(A13="","",XLOOKUP("BTC",tblKoersen[Symbol],tblKoersen[EUR prijs],0)) | F13: =IF(A13="","",C13*E13) | G13: =IF(OR(A13="",F13=0),"",D13/F13) | H13: =IF(A13="","",IF(XLOOKUP(A13,tblLeningen[LoanID],tblLeningen[LiquidatieLTV],"")="",XLOOKUP("DefaultLiquidationLTV_BTC",tblSettings[Parameter],tblSettings[Waarde]),XLOOKUP(A13,tblLeningen[LoanID],tblLeningen[LiquidatieLTV]))) | I13: =IF(OR(A13="",G13=""),"",H13-G13) | J13: =IF(A13="","",IF(I13<=XLOOKUP("RiskBuffer_BTC",tblSettings[Parameter],tblSettings[Waarde]),"RISK",IF(I13<=XLOOKUP("AlertBuffer_BTC",tblSettings[Parameter],tblSettings[Waarde]),"ALERT","OK"))) | K13: =IF(OR(A13="",J13="OK"),"",MAX(0,D13-(XLOOKUP("TargetLTV_BTC",tblSettings[Parameter],tblSettings[Waarde])*F13))) | L13: =IF(OR(A13="",J13="OK"),"",MAX(0,(D13/XLOOKUP("TargetLTV_BTC",tblSettings[Parameter],tblSettings[Waarde])-F13)/E13))
A16: Stress Test Scenarios
A17: Scenario | B17: BTC Drop | C17: New BTC Price | D17: LoanID | E17: New LTV | F17: New Status
A18: Scenario 1 | B18: =XLOOKUP("StressBTCDown1",tblSettings[Parameter],tblSettings[Waarde]) | C18: =XLOOKUP("BTC",tblKoersen[Symbol],tblKoersen[EUR prijs])*(1+B18) | D18: =A4 | E18: =IF(D18="","",D4/(C4*$C$18)) | F18: =IF(D18="","",IF(E18>=H4,"LIQUIDATION",IF((H4-E18)<=XLOOKUP("RiskBuffer_BTC",tblSettings[Parameter],tblSettings[Waarde]),"RISK",IF((H4-E18)<=XLOOKUP("AlertBuffer_BTC",tblSettings[Parameter],tblSettings[Waarde]),"ALERT","OK"))))
A19: Scenario 2 | B19: =XLOOKUP("StressBTCDown2",tblSettings[Parameter],tblSettings[Waarde]) | C19: =XLOOKUP("BTC",tblKoersen[Symbol],tblKoersen[EUR prijs])*(1+B19) | D19: =A4 | E19: =IF(D19="","",D4/(C4*$C$19)) | F19: =IF(D19="","",IF(E19>=H4,"LIQUIDATION",IF((H4-E19)<=XLOOKUP("RiskBuffer_BTC",tblSettings[Parameter],tblSettings[Waarde]),"RISK",IF((H4-E19)<=XLOOKUP("AlertBuffer_BTC",tblSettings[Parameter],tblSettings[Waarde]),"ALERT","OK"))))

Sheet Cash & Overig
A1: Cash & Overig - Liquide Middelen
G2: Totaal Cash: | H2: =SUM(tblCash[Bedrag(EUR)])
A3: Datum | B3: Rekening/Platform | C3: Bedrag(EUR) | D3: Type | E3: Opmerking
A4: 2024-03-01 | B4: ING Betaalrekening | C4: 15000 | D4: Betaalrekening | G4: Maandlasten (inst.): | H4: =XLOOKUP("MonthlyExpenses",tblSettings[Parameter],tblSettings[Waarde])
A5: 2024-03-01 | B5: ING Spaarrekening | C5: 35000 | D5: Spaarrekening | E5: Noodfonds | G5: Buffer (maanden): | H5: =IF(H4=0,0,H2/H4)
A6: 2024-03-01 | B6: DEGIRO | C6: 8000 | D6: Belegging | E6: ETF portfolio | G6: Target (maanden): | H6: =XLOOKUP("CashBufferMonthsTarget",tblSettings[Parameter],tblSettings[Waarde])

Sheet Inkomsten
A1: Inkomsten - Overzicht
I2: Totaal Bruto/maand: | J2: =SUM(tblInkomsten[Bruto/maand])
A3: Bron | B3: Omschrijving | C3: Bruto/maand | D3: Netto/maand | E3: Type | F3: Frequentie | G3: Opmerking | I3: Totaal Netto/maand: | J3: =SUM(tblInkomsten[Netto/maand])
A4: Salaris | B4: Werkgever | C4: 5500 | D4: 3800 | E4: Vast | F4: Maandelijks
A5: Huurinkomsten | B5: Appartement Utrecht | C5: 1400 | D5: 1200 | E5: Vastgoed | F5: Maandelijks | G5: Na kosten | I5: Jaarlijks Netto: | J5: =J3*12
A6: Dividend | B6: ETF portfolio | C6: 50 | D6: 50 | E6: Variabel | F6: Kwartaal | G6: Gemiddeld per maand

Sheet Maandlasten
A1: Maandlasten - Vaste Uitgaven
H2: Totaal/maand: | I2: =SUM(tblMaandlasten[Bedrag(EUR)])
A3: Categorie | B3: Omschrijving | C3: Bedrag(EUR) | D3: Frequentie | E3: Jaarlijks(EUR) | F3: Opmerking | H3: Totaal/jaar: | I3: =SUM(tblMaandlasten[Jaarlijks(EUR)])
A4: Wonen | B4: Hypotheek | C4: 1500 | D4: Maandelijks | E4: =IF(C4="","",IF(D4="Maandelijks",C4*12,IF(D4="Kwartaal",C4*4,IF(D4="Jaarlijks",C4,C4))))
A5: Wonen | B5: Energie (gas/elektra) | C5: 200 | D5: Maandelijks | E5: =IF(C5="","",IF(D5="Maandelijks",C5*12,IF(D5="Kwartaal",C5*4,IF(D5="Jaarlijks",C5,C5)))) | H5: Per categorie:
A6: Wonen | B6: Water | C6: 25 | D6: Maandelijks | E6: =IF(C6="","",IF(D6="Maandelijks",C6*12,IF(D6="Kwartaal",C6*4,IF(D6="Jaarlijks",C6,C6)))) | H6: Wonen | I6: =SUMIF(tblMaandlasten[Categorie],"Wonen",tblMaandlasten[Bedrag(EUR)])
A7: Wonen | B7: Gemeentebelasting | C7: 60 | D7: Maandelijks | E7: =IF(C7="","",IF(D7="Maandelijks",C7*12,IF(D7="Kwartaal",C7*4,IF(D7="Jaarlijks",C7,C7)))) | F7: OZB + afval + riool | H7: Verzekering | I7: =SUMIF(tblMaandlasten[Categorie],"Verzekering",tblMaandlasten[Bedrag(EUR)])
A8: Verzekering | B8: Zorgverzekering | C8: 140 | D8: Maandelijks | E8: =IF(C8="","",IF(D8="Maandelijks",C8*12,IF(D8="Kwartaal",C8*4,IF(D8="Jaarlijks",C8,C8)))) | H8: Vervoer | I8: =SUMIF(tblMaandlasten[Categorie],"Vervoer",tblMaandlasten[Bedrag(EUR)])
A9: Verzekering | B9: Inboedel + opstal | C9: 35 | D9: Maandelijks | E9: =IF(C9="","",IF(D9="Maandelijks",C9*12,IF(D9="Kwartaal",C9*4,IF(D9="Jaarlijks",C9,C9)))) | H9: Abonnement | I9: =SUMIF(tblMaandlasten[Categorie],"Abonnement",tblMaandlasten[Bedrag(EUR)])
A10: Verzekering | B10: Auto (WA + casco) | C10: 80 | D10: Maandelijks | E10: =IF(C10="","",IF(D10="Maandelijks",C10*12,IF(D10="Kwartaal",C10*4,IF(D10="Jaarlijks",C10,C10)))) | H10: Levensonderhoud | I10: =SUMIF(tblMaandlasten[Categorie],"Levensonderhoud",tblMaandlasten[Bedrag(EUR)])
A11: Vervoer | B11: Brandstof | C11: 150 | D11: Maandelijks | E11: =IF(C11="","",IF(D11="Maandelijks",C11*12,IF(D11="Kwartaal",C11*4,IF(D11="Jaarlijks",C11,C11)))) | H11: Overig | I11: =SUMIF(tblMaandlasten[Categorie],"Overig",tblMaandlasten[Bedrag(EUR)])
A12: Vervoer | B12: OV abonnement | C12: 100 | D12: Maandelijks | E12: =IF(C12="","",IF(D12="Maandelijks",C12*12,IF(D12="Kwartaal",C12*4,IF(D12="Jaarlijks",C12,C12))))
A13: Abonnement | B13: Internet + TV | C13: 60 | D13: Maandelijks | E13: =IF(C13="","",IF(D13="Maandelijks",C13*12,IF(D13="Kwartaal",C13*4,IF(D13="Jaarlijks",C13,C13))))
A14: Abonnement | B14: Telefoon | C14: 30 | D14: Maandelijks | E14: =IF(C14="","",IF(D14="Maandelijks",C14*12,IF(D14="Kwartaal",C14*4,IF(D14="Jaarlijks",C14,C14))))
A15: Abonnement | B15: Streaming (Netflix etc) | C15: 25 | D15: Maandelijks | E15: =IF(C15="","",IF(D15="Maandelijks",C15*12,IF(D15="Kwartaal",C15*4,IF(D15="Jaarlijks",C15,C15))))
A16: Levensonderhoud | B16: Boodschappen | C16: 500 | D16: Maandelijks | E16: =IF(C16="","",IF(D16="Maandelijks",C16*12,IF(D16="Kwartaal",C16*4,IF(D16="Jaarlijks",C16,C16))))
A17: Levensonderhoud | B17: Kleding | C17: 100 | D17: Maandelijks | E17: =IF(C17="","",IF(D17="Maandelijks",C17*12,IF(D17="Kwartaal",C17*4,IF(D17="Jaarlijks",C17,C17)))) | F17: Gemiddeld
A18: Overig | B18: Reservering onvoorzien | C18: 200 | D18: Maandelijks | E18: =IF(C18="","",IF(D18="Maandelijks",C18*12,IF(D18="Kwartaal",C18*4,IF(D18="Jaarlijks",C18,C18))))
E19: =IF(C19="","",IF(D19="Maandelijks",C19*12,IF(D19="Kwartaal",C19*4,IF(D19="Jaarlijks",C19,C19))))
E20: =IF(C20="","",IF(D20="Maandelijks",C20*12,IF(D20="Kwartaal",C20*4,IF(D20="Jaarlijks",C20,C20))))
E21: =IF(C21="","",IF(D21="Maandelijks",C21*12,IF(D21="Kwartaal",C21*4,IF(D21="Jaarlijks",C21,C21))))
E22: =IF(C22="","",IF(D22="Maandelijks",C22*12,IF(D22="Kwartaal",C22*4,IF(D22="Jaarlijks",C22,C22))))
E23: =IF(C23="","",IF(D23="Maandelijks",C23*12,IF(D23="Kwartaal",C23*4,IF(D23="Jaarlijks",C23,C23))))
E24: =IF(C24="","",IF(D24="Maandelijks",C24*12,IF(D24="Kwartaal",C24*4,IF(D24="Jaarlijks",C24,C24))))
E25: =IF(C25="","",IF(D25="Maandelijks",C25*12,IF(D25="Kwartaal",C25*4,IF(D25="Jaarlijks",C25,C25))))
E26: =IF(C26="","",IF(D26="Maandelijks",C26*12,IF(D26="Kwartaal",C26*4,IF(D26="Jaarlijks",C26,C26))))
E27: =IF(C27="","",IF(D27="Maandelijks",C27*12,IF(D27="Kwartaal",C27*4,IF(D27="Jaarlijks",C27,C27))))
E28: =IF(C28="","",IF(D28="Maandelijks",C28*12,IF(D28="Kwartaal",C28*4,IF(D28="Jaarlijks",C28,C28))))
E29: =IF(C29="","",IF(D29="Maandelijks",C29*12,IF(D29="Kwartaal",C29*4,IF(D29="Jaarlijks",C29,C29))))
E30: =IF(C30="","",IF(D30="Maandelijks",C30*12,IF(D30="Kwartaal",C30*4,IF(D30="Jaarlijks",C30,C30))))
... E49: =IF(C49="","",IF(D49="Maandelijks",C49*12,IF(D49="Kwartaal",C49*4,IF(D49="Jaarlijks",C49,C49))))

Sheet Belastingen
A1: Belastingen - Box 3 Vermogensbelasting (NL)
A2: Peildatum: 1 januari | Tarieven 2025 | Heffingsvrij vermogen: €57.684 p.p.
A4: Vermogenstype | B4: Waarde 1 jan | C4: Forfaitair % | D4: Fictief rendement | E4: Opmerking
A5: Spaargeld | B5: =SUM(tblCash[Bedrag(EUR)]) | C5: 0.0092 | D5: =B5*C5 | E5: spaar
A6: Beleggingen (excl. crypto) | B6: =SUMIF(tblCash[Type],"Belegging",tblCash[Bedrag(EUR)]) | C6: 0.0617 | D6: =B6*C6 | E6: beleg
A7: Crypto (BTC + DOGE) | B7: =SUM(tblBTC[BTC Aantal])*XLOOKUP("BTC",tblKoersen[Symbol],tblKoersen[EUR prijs],0)+SUM(tblDOGE[DOGE Aantal])*XLOOKUP("DOGE",tblKoersen[Symbol],tblKoersen[EUR prijs],0) | C7: 0.0617 | D7: =B7*C7 | E7: beleg
A8: Vastgoed (WOZ-waarde) | B8: =SUM(tblVastgoed[Waarde(EUR)]) | C8: 0.0617 | D8: =B8*C8 | E8: Let op: eigen woning in Box 1
A9: Schulden (aftrekbaar) | B9: =-SUM(tblLeningen[Openstaand(EUR)])-SUM(tblVastgoed[Hypotheek(EUR)])-SUM(tblVastgoed[Overige Leningen(EUR)]) | C9: 0.0257 | D9: =B9*C9 | E9: Drempel €3.700
A11: TOTAAL VERMOGEN | B11: =SUM(B5:B9)
A12: Heffingsvrij vermogen | B12: 57684 | E12: Per persoon, fiscale partners: x2
A13: Belastbaar vermogen | B13: =MAX(0,B11-B12)
A15: Totaal fictief rendement | D15: =SUM(D5:D9)
A17: BOX 3 BELASTING
A18: Fictief rendement | B18: =D14
A19: Belastingtarief | B19: 0.36
A20: TE BETALEN BOX 3 | B20: =B18*B19
A23: LET OP:
A24: • Dit is een INDICATIEVE berekening, geen belastingadvies
A25: • Eigen woning valt normaal in Box 1, niet Box 3
A26: • Schulden hebben een drempel van €3.700 (2025)
A27: • Fiscale partners kunnen heffingsvrij vermogen optellen (€115.368)
A28: • Crypto wordt door de Belastingdienst als 'overige bezitting' gezien
A29: • Peildatum is altijd 1 januari van het belastingjaar
